LICENSE
README.md
setup.cfg
setup.py
pokie_container/__init__.py
pokie_container/constants.py
pokie_container/errors.py
pokie_container/module.py
pokie_container.egg-info/PKG-INFO
pokie_container.egg-info/SOURCES.txt
pokie_container.egg-info/dependency_links.txt
pokie_container.egg-info/not-zip-safe
pokie_container.egg-info/requires.txt
pokie_container.egg-info/top_level.txt
pokie_container/cli/__init__.py
pokie_container/dto/__init__.py
pokie_container/dto/dto.py
pokie_container/repository/__init__.py
pokie_container/repository/repository.py
pokie_container/service/__init__.py
pokie_container/service/container.py
tests/__init__.py
tests/service/__init__.py
tests/service/test_container.py